<?xml version="1.0" encoding="utf-16"?>
<meta>
  <info type="map" gamemodes="race" name="3756" author="Suilenroc" description="Evade the hunters and make it safely to your hideout on grove street after dropping the money off in San Fierro.  Most of the roads out of Las Venturas are blocked.  Use common sense to find repair, nitro, and vehicle pickups." />
  <map src="3756.map" />
  <settings>
    <setting name="#time" value="0:0" />
    <setting name="#respawn" value="timelimit" />
    <setting name="#respawntime" value="30" />
    <setting name="#duration" value="1500" />
  </settings>
</meta>