<?xml version="1.0" encoding="utf-16"?>
<meta>
  <info type="map" gamemodes="race" name="3091" author="DiddRunn" description="4 minutes, 1-car street race around East LS with some crossing ramps, fences and alternative ways. Old-school fun. (feedback appreciated)" />
  <map src="3091.map" />
  <settings>
    <setting name="#time" value="1:25" />
    <setting name="#weather" value="1" />
    <setting name="#respawn" value="timelimit" />
    <setting name="#respawntime" value="6" />
    <setting name="#duration" value="300" />
  </settings>
</meta>